setup.py
csv_splitter/__init__.py
csv_splitter.egg-info/PKG-INFO
csv_splitter.egg-info/SOURCES.txt
csv_splitter.egg-info/dependency_links.txt
csv_splitter.egg-info/not-zip-safe
csv_splitter.egg-info/top_level.txt