Metadata-Version: 1.0
Name: csv-splitter
Version: 0.0.1
Summary: Split csv files.
Home-page: https://github.com/estranium/csv_splitter
Author: Dmitry Shevelev
Author-email: estranium@gmail.com
License: MIT
Platform: UNKNOWN
